odoo8_addon_account_fiscal_position_rule_sale-8.0.1.1.1.99.dev19-py3.8-nspkg.pth
odoo_addons/account_fiscal_position_rule_sale/__init__.py
odoo_addons/account_fiscal_position_rule_sale/__openerp__.py
odoo_addons/account_fiscal_position_rule_sale/i18n/account_fiscal_position_rule_sale.pot
odoo_addons/account_fiscal_position_rule_sale/i18n/ca.po
odoo_addons/account_fiscal_position_rule_sale/i18n/de.po
odoo_addons/account_fiscal_position_rule_sale/i18n/en_US.po
odoo_addons/account_fiscal_position_rule_sale/i18n/es.po
odoo_addons/account_fiscal_position_rule_sale/i18n/es_ES.po
odoo_addons/account_fiscal_position_rule_sale/i18n/fi.po
odoo_addons/account_fiscal_position_rule_sale/i18n/fr.po
odoo_addons/account_fiscal_position_rule_sale/i18n/hr.po
odoo_addons/account_fiscal_position_rule_sale/i18n/hu.po
odoo_addons/account_fiscal_position_rule_sale/i18n/it.po
odoo_addons/account_fiscal_position_rule_sale/i18n/nl.po
odoo_addons/account_fiscal_position_rule_sale/i18n/nl_NL.po
odoo_addons/account_fiscal_position_rule_sale/i18n/pt_BR.po
odoo_addons/account_fiscal_position_rule_sale/i18n/ro.po
odoo_addons/account_fiscal_position_rule_sale/i18n/sk.po
odoo_addons/account_fiscal_position_rule_sale/i18n/sl.po
odoo_addons/account_fiscal_position_rule_sale/i18n/tr.po
odoo_addons/account_fiscal_position_rule_sale/i18n/tr_TR.po
odoo_addons/account_fiscal_position_rule_sale/i18n/zh_CN.po
odoo_addons/account_fiscal_position_rule_sale/models/__init__.py
odoo_addons/account_fiscal_position_rule_sale/models/sale.py
odoo_addons/account_fiscal_position_rule_sale/security/ir.model.access.csv
odoo_addons/account_fiscal_position_rule_sale/static/description/icon.png
odoo_addons/account_fiscal_position_rule_sale/views/sale_view.xml
odoo8_addon_account_fiscal_position_rule_sale-8.0.1.1.1.99.dev19.dist-info/METADATA
odoo8_addon_account_fiscal_position_rule_sale-8.0.1.1.1.99.dev19.dist-info/WHEEL
odoo8_addon_account_fiscal_position_rule_sale-8.0.1.1.1.99.dev19.dist-info/namespace_packages.txt
odoo8_addon_account_fiscal_position_rule_sale-8.0.1.1.1.99.dev19.dist-info/top_level.txt
odoo8_addon_account_fiscal_position_rule_sale-8.0.1.1.1.99.dev19.dist-info/RECORD
